cryptobeacon/__init__.py
cryptobeacon/assets/__init__.py
cryptobeacon/assets/beacon.ico
cryptobeacon/commands/__init__.py
cryptobeacon/commands/alarm.py
cryptobeacon/commands/coin.py
cryptobeacon/main.py
cryptobeacon/utils/__init__.py
cryptobeacon/utils/apis.py
cryptobeacon/utils/coins.py
cryptobeacon-1.0.1.dist-info/entry_points.txt
cryptobeacon-1.0.1.dist-info/WHEEL
cryptobeacon-1.0.1.dist-info/METADATA
cryptobeacon-1.0.1.dist-info/RECORD
