Metadata-Version: 2.1
Name: cryptobeacon
Version: 1.0.1
Summary: CryptoBeacon is a simple command-line interface tool for cryptocurrency alerts directly into your desktop.
License: MIT
Author: Eduardo V. e Sousa
Author-email: eduardoatrcomp@gmail.com
Requires-Python: >=3.10,<4.0
Classifier: License :: OSI Approved :: MIT License
Classifier: Programming Language :: Python :: 3
Classifier: Programming Language :: Python :: 3.10
Requires-Dist: requests (>=2.28.0,<3.0.0)
Requires-Dist: rich (>=12.4.4,<13.0.0)
Requires-Dist: typer[all] (>=0.4.1,<0.5.0)
